<?xml version="1.0" encoding="UTF-8" standalone="no"?>
<event category="OTHER" id="11">
  <actions>
    <action id="603" library="1">
      <!--action name: Code-->
      <kind>CODE</kind>
      <allowRelative>false</allowRelative>
      <question>false</question>
      <canApplyTo>true</canApplyTo>
      <actionType>CODE</actionType>
      <functionName/>
      <relative>false</relative>
      <not>false</not>
      <appliesTo>.self</appliesTo>
      <arguments>
        <argument kind="STRING">{
    if (readyToShoot and ammoCount &gt; 0)
    {
        ammoCount -= 1;
        playsound(x,y,MedichaingunSnd);
        var shot;
        shot = createShot(x, y + yoffset + 1, Needle, DAMAGE_SOURCE_NEEDLEGUN, owner.aimDirection, 7+random(3));
        shot.hitDamage = 4;
        justShot=true;
        with(shot)
            hspeed+=owner.hspeed;
        readyToShoot=false;
        alarm[0] = refireTime / global.delta_factor;
        alarm[5] = (reloadBuffer + reloadTime) / global.delta_factor;
        alarm[7] = alarm[5] / 4;
    }
}
</argument>
      </arguments>
    </action>
  </actions>
</event>
